mcot/__init__.py
mcot/maths/README.rst
mcot/maths/VERSION
mcot/maths/__init__.py
mcot/maths/spherical.py
mcot.maths-0.1.0.dist-info/METADATA
mcot.maths-0.1.0.dist-info/WHEEL
mcot.maths-0.1.0.dist-info/namespace_packages.txt
mcot.maths-0.1.0.dist-info/top_level.txt
mcot.maths-0.1.0.dist-info/RECORD
